mindchat/__init__.py
mindchat_mv-0.2.dist-info/LICENSE.txt
mindchat_mv-0.2.dist-info/METADATA
mindchat_mv-0.2.dist-info/WHEEL
mindchat_mv-0.2.dist-info/top_level.txt
mindchat_mv-0.2.dist-info/RECORD
