Metadata-Version: 2.1
Name: mindchat-mv
Version: 0.2
Summary: enter key,set_parameters,qna
Home-page: UNKNOWN
Author: Prince Kathuria
Author-email: pk.kathuria9213@gmail.com
License: UNKNOWN
Platform: UNKNOWN
Classifier: Programming Language :: Python :: 3
Classifier: License :: OSI Approved :: MIT License
License-File: LICENSE.txt
